Piler/Piler.py
Piler/__init__.py
Piler/pilerFunctions.py
tns_piler-0.0.4.dist-info/LICENSE
tns_piler-0.0.4.dist-info/METADATA
tns_piler-0.0.4.dist-info/WHEEL
tns_piler-0.0.4.dist-info/entry_points.txt
tns_piler-0.0.4.dist-info/top_level.txt
tns_piler-0.0.4.dist-info/RECORD
