Metadata-Version: 2.1
Name: tns-piler
Version: 0.0.4
Summary: Tool for finding cumulative pileups
Home-page: https://github.com/TimNicholsonShaw/piler
Author: Tim Nicholson-Shaw
Author-email: timnicholsonshaw@gmail.com
License: UNKNOWN
Project-URL: Lab Website, https://labs.biology.ucsd.edu/lykkeandersen/index.html
Keywords: Sequencing,Bioinformatics
Platform: UNKNOWN
Classifier: Development Status :: 3 - Alpha
Classifier: License :: OSI Approved :: MIT License
Classifier: Programming Language :: Python :: 3 :: Only
Requires-Python: >=3.6
License-File: LICENSE
Requires-Dist: pysam
Requires-Dist: gffutils
